dophon_cloud/__init__.py
dophon_cloud/enhance_pkg/__init__.py
dophon_cloud/enhance_pkg/const.py
dophon_cloud/enhance_pkg/decrate_enhance.py
dophon_cloud/eureka_client/__init__.py
dophon_cloud/eureka_client/__urlopen_proxy__.py
dophon_cloud/eureka_client/eureka_client.py
dophon_cloud/eureka_client/eureka_client_urllib3.py
dophon_cloud/utils/__init__.py
dophon_cloud-1.0.3.dist-info/LICENSE
dophon_cloud-1.0.3.dist-info/WHEEL
dophon_cloud-1.0.3.dist-info/METADATA
dophon_cloud-1.0.3.dist-info/RECORD
