Metadata-Version: 2.1
Name: dophon-cloud
Version: 1.0.3
Summary: dophon cloud(import reg center)
Home-page: UNKNOWN
License: UNKNOWN
Author: CallMeE
Author-email: ealohu@163.com
Classifier: Programming Language :: Python :: 2
Classifier: Programming Language :: Python :: 2.7
Classifier: Programming Language :: Python :: 3
Classifier: Programming Language :: Python :: 3.4
Classifier: Programming Language :: Python :: 3.5
Classifier: Programming Language :: Python :: 3.6
Classifier: Programming Language :: Python :: 3.7
Requires-Dist: dophon
Requires-Dist: dophon_cloud_center
Requires-Dist: py_eureka_client
